radt/__init__.py
radt/__main__.py
radt/constants.py
radt/radt.py
radt/run/__init__.py
radt/run/benchmark.py
radt/run/run.py
radt/run/listeners/__init__.py
radt/run/listeners/dcgmi_listener.py
radt/run/listeners/free_listener.py
radt/run/listeners/iostat_listener.py
radt/run/listeners/macmon_listener.py
radt/run/listeners/ps_listener.py
radt/run/listeners/smi_listener.py
radt/run/listeners/top_listener.py
radt/schedule/__init__.py
radt/schedule/schedule.py
radt-0.2.24.dist-info/entry_points.txt
radt-0.2.24.dist-info/WHEEL
radt-0.2.24.dist-info/METADATA
radt-0.2.24.dist-info/RECORD
