Metadata-Version: 2.4
Name: radt
Version: 0.2.24
Summary: Resource-Aware Data systems Tracker (radT) for automatically tracking and training machine learning software.
Author-email: Ties Robroek <titr@itu.dk>
Classifier: License :: OSI Approved :: MIT License
Requires-Dist: mlflow >=2.4.0
Requires-Dist: pandas >=2.0.0
Requires-Dist: migedit >= 0.2.0
Requires-Dist: boto3 >= 1.25.0
Project-URL: Home, https://github.com/Resource-Aware-Data-systems-RAD/radt
